antiless/__init__.py
antiless/colors.py
antiless/console.py
antiless/legacy.py
antiless/log.py
antiless/unique.py
antiless-0.9.dist-info/METADATA
antiless-0.9.dist-info/WHEEL
antiless-0.9.dist-info/top_level.txt
antiless-0.9.dist-info/RECORD
