Metadata-Version: 2.1
Name: antiless
Version: 0.9
Summary: antiless // antilag
Home-page: http://pypi.python.org/pypi/antiless
Author: antilag
Author-email: antilagbest@gmail.com
License: MIT
Project-URL: Homepage, https://github.com/antilagg/antiless
Project-URL: Suggestions, https://github.com/antilagg/antiless/issues
Classifier: Development Status :: 3 - Alpha
Classifier: Intended Audience :: Developers
Classifier: License :: OSI Approved :: MIT License
Classifier: Natural Language :: English
Classifier: Programming Language :: Python
Classifier: Programming Language :: Python :: 3
Classifier: Programming Language :: Python :: 3.8
Classifier: Programming Language :: Python :: 3.9
Classifier: Programming Language :: Python :: 3.10
Classifier: Programming Language :: Python :: 3.11
Classifier: Topic :: Scientific/Engineering
Classifier: Topic :: Scientific/Engineering :: Information Analysis
Classifier: Topic :: Scientific/Engineering :: Mathematics
Classifier: Topic :: Scientific/Engineering :: Visualization
Classifier: Topic :: Software Development :: Libraries
Classifier: Topic :: Utilities
Requires-Python: ~=3.8
Requires-Dist: colorama >=0.6.6
Requires-Dist: requests >=2.30.0
